Metadata-Version: 2.1
Name: cpp-uuid
Version: 1.0.1
Summary: Python UUID module written in C++
Author-email: Dmitriy Makeev <makeev.dimitry@gmail.com>
License: MIT License
Project-URL: Source, https://github.com/DmitriyMakeev/cpp_uuid
Keywords: python3,fast,uuid,uuid4,c++,cpp
Classifier: License :: OSI Approved :: MIT License
Classifier: Programming Language :: Python
Classifier: Programming Language :: Python :: 3
Requires-Python: >=3.8
License-File: LICENSE
